SBTi/__init__.py
SBTi/configs.py
SBTi/interfaces.py
SBTi/portfolio_aggregation.py
SBTi/portfolio_coverage_tvp.py
SBTi/target_validation.py
SBTi/target_valuation_protocol.py
SBTi/temperature_score.py
SBTi/utils.py
SBTi/data/__init__.py
SBTi/data/bloomberg.py
SBTi/data/cdp.py
SBTi/data/csv.py
SBTi/data/data_provider.py
SBTi/data/excel.py
SBTi/data/iss.py
SBTi/data/msci.py
SBTi/data/sbti.py
SBTi/data/trucost.py
SBTi/data/urgentem.py
SBTi/data/urgentum.py
SBTi/inputs/current-Companies-Taking-Action-191.xlsx
SBTi/inputs/regression_model_summary.xlsx
SBTi/inputs/sr15_mapping.xlsx
app/__init__.py
app/app_server.py
app/wsgi.py
SBTi-1.0.dist-info/LICENSE
SBTi-1.0.dist-info/METADATA
SBTi-1.0.dist-info/WHEEL
SBTi-1.0.dist-info/licenses_overview.md
SBTi-1.0.dist-info/top_level.txt
SBTi-1.0.dist-info/RECORD
