Metadata-Version: 2.1
Name: SBTi
Version: 1.0
Summary: This package helps companies and financial institutions to assess the temperature alignment of currenttargets, commitments, and investment and lending portfolios, and to use this information to develop targets for official validation by the SBTi.
Home-page: https://ofbdabv.github.io/SBTi/
Author: Ortec Finance
Author-email: finance@sciencebasedtargets.org
License: UNKNOWN
Download-URL: https://pypi.org/project/SBTi-Finance-Temperature-Alignment-Tool/
Project-URL: Bug Tracker, https://github.com/OFBDABV/SBTi/issues
Project-URL: Documentation, https://ofbdabv.github.io/SBTi/
Project-URL: Source Code, https://github.com/OFBDABV/SBTi/
Keywords: Climate,SBTi,Finance
Platform: UNKNOWN
Classifier: Programming Language :: Python :: 3
Classifier: License :: OSI Approved :: MIT License
Classifier: Operating System :: Microsoft :: Windows
Classifier: Operating System :: Unix
Classifier: Operating System :: MacOS
Classifier: Intended Audience :: Science/Research
Classifier: Intended Audience :: Developers
Classifier: Programming Language :: Python
Classifier: Programming Language :: Python :: 3
Classifier: Programming Language :: Python :: 3.6
Classifier: Programming Language :: Python :: 3.7
Classifier: Programming Language :: Python :: 3.8
Classifier: Programming Language :: Python :: 3 :: Only
Classifier: Topic :: Software Development
Classifier: Topic :: Scientific/Engineering
Requires-Python: >=3.6
Requires-Dist: pandas
Requires-Dist: xlrd
Requires-Dist: pydantic
Provides-Extra: dev
Requires-Dist: nose2 ; extra == 'dev'
